CONTRIBUTING.md
COPYING
MANIFEST.in
NEWS.md
README.md
python-bugzilla.spec
requirements.txt
setup.py
test-requirements.txt
bugzilla/__init__.py
bugzilla/_authfiles.py
bugzilla/_backendbase.py
bugzilla/_backendrest.py
bugzilla/_backendxmlrpc.py
bugzilla/_cli.py
bugzilla/_rhconverters.py
bugzilla/_session.py
bugzilla/_util.py
bugzilla/apiversion.py
bugzilla/base.py
bugzilla/bug.py
bugzilla/exceptions.py
bugzilla/oldclasses.py
bugzilla/rhbugzilla.py
examples/apikey.py
examples/bug_autorefresh.py
examples/create.py
examples/getbug.py
examples/getbug_restapi.py
examples/query.py
examples/redhat_query_all.py
examples/update.py
man/bugzilla.1
man/bugzilla.rst
python_bugzilla.egg-info/PKG-INFO
python_bugzilla.egg-info/SOURCES.txt
python_bugzilla.egg-info/dependency_links.txt
python_bugzilla.egg-info/entry_points.txt
python_bugzilla.egg-info/requires.txt
python_bugzilla.egg-info/top_level.txt
tests/__init__.py
tests/conftest.py
tests/mockbackend.py
tests/pycodestyle.cfg
tests/test_api_attachments.py
tests/test_api_authfiles.py
tests/test_api_bug.py
tests/test_api_externalbugs.py
tests/test_api_groups.py
tests/test_api_misc.py
tests/test_api_products.py
tests/test_api_users.py
tests/test_backend_rest.py
tests/test_base.py
tests/test_cli_attach.py
tests/test_cli_info.py
tests/test_cli_login.py
tests/test_cli_misc.py
tests/test_cli_modify.py
tests/test_cli_new.py
tests/test_cli_query.py
tests/test_ro_functional.py
tests/test_rw_functional.py
tests/utils.py
tests/data/bz-attach-get1.txt
tests/data/components_file.txt
tests/data/authfiles/output-bugzillarc.txt
tests/data/authfiles/output-token.txt
tests/data/clioutput/test_info_components-active.txt
tests/data/clioutput/test_info_components-owners.txt
tests/data/clioutput/test_info_components.txt
tests/data/clioutput/test_info_products.txt
tests/data/clioutput/test_info_versions.txt
tests/data/clioutput/test_interactive_login_apikey_rcfile.txt
tests/data/clioutput/test_json_xmlrpc.txt
tests/data/clioutput/test_new1.txt
tests/data/clioutput/test_new2.txt
tests/data/clioutput/test_query1-ids.txt
tests/data/clioutput/test_query1-rhbz.txt
tests/data/clioutput/test_query1.txt
tests/data/clioutput/test_query10.txt
tests/data/clioutput/test_query2-rhbz.txt
